<?xml version="1.0"?>
<category><title>Miao</title><characters><item0><title>Miao Letter Pa</title><code>&amp;#93952;</code></item0><item1><title>Miao Letter Ba</title><code>&amp;#93953;</code></item1><item2><title>Miao Letter Yi Pa</title><code>&amp;#93954;</code></item2><item3><title>Miao Letter Pla</title><code>&amp;#93955;</code></item3><item4><title>Miao Letter Ma</title><code>&amp;#93956;</code></item4><item5><title>Miao Letter Mha</title><code>&amp;#93957;</code></item5><item6><title>Miao Letter Archaic Ma</title><code>&amp;#93958;</code></item6><item7><title>Miao Letter Fa</title><code>&amp;#93959;</code></item7><item8><title>Miao Letter Va</title><code>&amp;#93960;</code></item8><item9><title>Miao Letter Vfa</title><code>&amp;#93961;</code></item9><item10><title>Miao Letter Ta</title><code>&amp;#93962;</code></item10><item11><title>Miao Letter Da</title><code>&amp;#93963;</code></item11><item12><title>Miao Letter Yi Tta</title><code>&amp;#93964;</code></item12><item13><title>Miao Letter Yi Ta</title><code>&amp;#93965;</code></item13><item14><title>Miao Letter Tta</title><code>&amp;#93966;</code></item14><item15><title>Miao Letter Dda</title><code>&amp;#93967;</code></item15><item16><title>Miao Letter Na</title><code>&amp;#93968;</code></item16><item17><title>Miao Letter Nha</title><code>&amp;#93969;</code></item17><item18><title>Miao Letter Yi Nna</title><code>&amp;#93970;</code></item18><item19><title>Miao Letter Archaic Na</title><code>&amp;#93971;</code></item19><item20><title>Miao Letter Nna</title><code>&amp;#93972;</code></item20><item21><title>Miao Letter Nnha</title><code>&amp;#93973;</code></item21><item22><title>Miao Letter La</title><code>&amp;#93974;</code></item22><item23><title>Miao Letter Lya</title><code>&amp;#93975;</code></item23><item24><title>Miao Letter Lha</title><code>&amp;#93976;</code></item24><item25><title>Miao Letter Lhya</title><code>&amp;#93977;</code></item25><item26><title>Miao Letter Tlha</title><code>&amp;#93978;</code></item26><item27><title>Miao Letter Dlha</title><code>&amp;#93979;</code></item27><item28><title>Miao Letter Tlhya</title><code>&amp;#93980;</code></item28><item29><title>Miao Letter Dlhya</title><code>&amp;#93981;</code></item29><item30><title>Miao Letter Ka</title><code>&amp;#93982;</code></item30><item31><title>Miao Letter Ga</title><code>&amp;#93983;</code></item31><item32><title>Miao Letter Yi Ka</title><code>&amp;#93984;</code></item32><item33><title>Miao Letter Qa</title><code>&amp;#93985;</code></item33><item34><title>Miao Letter Qga</title><code>&amp;#93986;</code></item34><item35><title>Miao Letter Nga</title><code>&amp;#93987;</code></item35><item36><title>Miao Letter Ngha</title><code>&amp;#93988;</code></item36><item37><title>Miao Letter Archaic Nga</title><code>&amp;#93989;</code></item37><item38><title>Miao Letter Ha</title><code>&amp;#93990;</code></item38><item39><title>Miao Letter Xa</title><code>&amp;#93991;</code></item39><item40><title>Miao Letter Gha</title><code>&amp;#93992;</code></item40><item41><title>Miao Letter Ghha</title><code>&amp;#93993;</code></item41><item42><title>Miao Letter Tssa</title><code>&amp;#93994;</code></item42><item43><title>Miao Letter Dzza</title><code>&amp;#93995;</code></item43><item44><title>Miao Letter Nya</title><code>&amp;#93996;</code></item44><item45><title>Miao Letter Nyha</title><code>&amp;#93997;</code></item45><item46><title>Miao Letter Tsha</title><code>&amp;#93998;</code></item46><item47><title>Miao Letter Dzha</title><code>&amp;#93999;</code></item47><item48><title>Miao Letter Yi Tsha</title><code>&amp;#94000;</code></item48><item49><title>Miao Letter Yi Dzha</title><code>&amp;#94001;</code></item49><item50><title>Miao Letter Reformed Tsha</title><code>&amp;#94002;</code></item50><item51><title>Miao Letter Sha</title><code>&amp;#94003;</code></item51><item52><title>Miao Letter Ssa</title><code>&amp;#94004;</code></item52><item53><title>Miao Letter Zha</title><code>&amp;#94005;</code></item53><item54><title>Miao Letter Zsha</title><code>&amp;#94006;</code></item54><item55><title>Miao Letter Tsa</title><code>&amp;#94007;</code></item55><item56><title>Miao Letter Dza</title><code>&amp;#94008;</code></item56><item57><title>Miao Letter Yi Tsa</title><code>&amp;#94009;</code></item57><item58><title>Miao Letter Sa</title><code>&amp;#94010;</code></item58><item59><title>Miao Letter Za</title><code>&amp;#94011;</code></item59><item60><title>Miao Letter Zsa</title><code>&amp;#94012;</code></item60><item61><title>Miao Letter Zza</title><code>&amp;#94013;</code></item61><item62><title>Miao Letter Zzsa</title><code>&amp;#94014;</code></item62><item63><title>Miao Letter Archaic Zza</title><code>&amp;#94015;</code></item63><item64><title>Miao Letter Zzya</title><code>&amp;#94016;</code></item64><item65><title>Miao Letter Zzsya</title><code>&amp;#94017;</code></item65><item66><title>Miao Letter Wa</title><code>&amp;#94018;</code></item66><item67><title>Miao Letter Ah</title><code>&amp;#94019;</code></item67><item68><title>Miao Letter Hha</title><code>&amp;#94020;</code></item68><item69><title>Utf-8 Character</title><code>&amp;#94021;</code></item69><item70><title>Utf-8 Character</title><code>&amp;#94022;</code></item70><item71><title>Utf-8 Character</title><code>&amp;#94023;</code></item71><item72><title>Utf-8 Character</title><code>&amp;#94024;</code></item72><item73><title>Utf-8 Character</title><code>&amp;#94025;</code></item73><item74><title>Utf-8 Character</title><code>&amp;#94026;</code></item74><item75><title>Utf-8 Character</title><code>&amp;#94027;</code></item75><item76><title>Utf-8 Character</title><code>&amp;#94028;</code></item76><item77><title>Utf-8 Character</title><code>&amp;#94029;</code></item77><item78><title>Utf-8 Character</title><code>&amp;#94030;</code></item78><item79><title>Utf-8 Character</title><code>&amp;#94031;</code></item79><item80><title>Miao Letter Nasalization</title><code>&amp;#94032;</code></item80><item81><title>Miao Sign Aspiration</title><code>&amp;#94033;</code></item81><item82><title>Miao Sign Reformed Voicing</title><code>&amp;#94034;</code></item82><item83><title>Miao Sign Reformed Aspiration</title><code>&amp;#94035;</code></item83><item84><title>Miao Vowel Sign A</title><code>&amp;#94036;</code></item84><item85><title>Miao Vowel Sign Aa</title><code>&amp;#94037;</code></item85><item86><title>Miao Vowel Sign Ahh</title><code>&amp;#94038;</code></item86><item87><title>Miao Vowel Sign An</title><code>&amp;#94039;</code></item87><item88><title>Miao Vowel Sign Ang</title><code>&amp;#94040;</code></item88><item89><title>Miao Vowel Sign O</title><code>&amp;#94041;</code></item89><item90><title>Miao Vowel Sign Oo</title><code>&amp;#94042;</code></item90><item91><title>Miao Vowel Sign Wo</title><code>&amp;#94043;</code></item91><item92><title>Miao Vowel Sign W</title><code>&amp;#94044;</code></item92><item93><title>Miao Vowel Sign E</title><code>&amp;#94045;</code></item93><item94><title>Miao Vowel Sign En</title><code>&amp;#94046;</code></item94><item95><title>Miao Vowel Sign Eng</title><code>&amp;#94047;</code></item95><item96><title>Miao Vowel Sign Oey</title><code>&amp;#94048;</code></item96><item97><title>Miao Vowel Sign I</title><code>&amp;#94049;</code></item97><item98><title>Miao Vowel Sign Ia</title><code>&amp;#94050;</code></item98><item99><title>Miao Vowel Sign Ian</title><code>&amp;#94051;</code></item99><item100><title>Miao Vowel Sign Iang</title><code>&amp;#94052;</code></item100><item101><title>Miao Vowel Sign Io</title><code>&amp;#94053;</code></item101><item102><title>Miao Vowel Sign Ie</title><code>&amp;#94054;</code></item102><item103><title>Miao Vowel Sign Ii</title><code>&amp;#94055;</code></item103><item104><title>Miao Vowel Sign Iu</title><code>&amp;#94056;</code></item104><item105><title>Miao Vowel Sign Ing</title><code>&amp;#94057;</code></item105><item106><title>Miao Vowel Sign U</title><code>&amp;#94058;</code></item106><item107><title>Miao Vowel Sign Ua</title><code>&amp;#94059;</code></item107><item108><title>Miao Vowel Sign Uan</title><code>&amp;#94060;</code></item108><item109><title>Miao Vowel Sign Uang</title><code>&amp;#94061;</code></item109><item110><title>Miao Vowel Sign Uu</title><code>&amp;#94062;</code></item110><item111><title>Miao Vowel Sign Uei</title><code>&amp;#94063;</code></item111><item112><title>Miao Vowel Sign Ung</title><code>&amp;#94064;</code></item112><item113><title>Miao Vowel Sign Y</title><code>&amp;#94065;</code></item113><item114><title>Miao Vowel Sign Yi</title><code>&amp;#94066;</code></item114><item115><title>Miao Vowel Sign Ae</title><code>&amp;#94067;</code></item115><item116><title>Miao Vowel Sign Aee</title><code>&amp;#94068;</code></item116><item117><title>Miao Vowel Sign Err</title><code>&amp;#94069;</code></item117><item118><title>Miao Vowel Sign Rounded Err</title><code>&amp;#94070;</code></item118><item119><title>Miao Vowel Sign Er</title><code>&amp;#94071;</code></item119><item120><title>Miao Vowel Sign Rounded Er</title><code>&amp;#94072;</code></item120><item121><title>Miao Vowel Sign Ai</title><code>&amp;#94073;</code></item121><item122><title>Miao Vowel Sign Ei</title><code>&amp;#94074;</code></item122><item123><title>Miao Vowel Sign Au</title><code>&amp;#94075;</code></item123><item124><title>Miao Vowel Sign Ou</title><code>&amp;#94076;</code></item124><item125><title>Miao Vowel Sign N</title><code>&amp;#94077;</code></item125><item126><title>Miao Vowel Sign Ng</title><code>&amp;#94078;</code></item126><item127><title>Utf-8 Character</title><code>&amp;#94079;</code></item127><item128><title>Utf-8 Character</title><code>&amp;#94080;</code></item128><item129><title>Utf-8 Character</title><code>&amp;#94081;</code></item129><item130><title>Utf-8 Character</title><code>&amp;#94082;</code></item130><item131><title>Utf-8 Character</title><code>&amp;#94083;</code></item131><item132><title>Utf-8 Character</title><code>&amp;#94084;</code></item132><item133><title>Utf-8 Character</title><code>&amp;#94085;</code></item133><item134><title>Utf-8 Character</title><code>&amp;#94086;</code></item134><item135><title>Utf-8 Character</title><code>&amp;#94087;</code></item135><item136><title>Utf-8 Character</title><code>&amp;#94088;</code></item136><item137><title>Utf-8 Character</title><code>&amp;#94089;</code></item137><item138><title>Utf-8 Character</title><code>&amp;#94090;</code></item138><item139><title>Utf-8 Character</title><code>&amp;#94091;</code></item139><item140><title>Utf-8 Character</title><code>&amp;#94092;</code></item140><item141><title>Utf-8 Character</title><code>&amp;#94093;</code></item141><item142><title>Utf-8 Character</title><code>&amp;#94094;</code></item142><item143><title>Miao Tone Right</title><code>&amp;#94095;</code></item143><item144><title>Miao Tone Top Right</title><code>&amp;#94096;</code></item144><item145><title>Miao Tone Above</title><code>&amp;#94097;</code></item145><item146><title>Miao Tone Below</title><code>&amp;#94098;</code></item146><item147><title>Miao Letter Tone-2</title><code>&amp;#94099;</code></item147><item148><title>Miao Letter Tone-3</title><code>&amp;#94100;</code></item148><item149><title>Miao Letter Tone-4</title><code>&amp;#94101;</code></item149><item150><title>Miao Letter Tone-5</title><code>&amp;#94102;</code></item150><item151><title>Miao Letter Tone-6</title><code>&amp;#94103;</code></item151><item152><title>Miao Letter Tone-7</title><code>&amp;#94104;</code></item152><item153><title>Miao Letter Tone-8</title><code>&amp;#94105;</code></item153><item154><title>Miao Letter Reformed Tone-1</title><code>&amp;#94106;</code></item154><item155><title>Miao Letter Reformed Tone-2</title><code>&amp;#94107;</code></item155><item156><title>Miao Letter Reformed Tone-4</title><code>&amp;#94108;</code></item156><item157><title>Miao Letter Reformed Tone-5</title><code>&amp;#94109;</code></item157><item158><title>Miao Letter Reformed Tone-6</title><code>&amp;#94110;</code></item158><item159><title>Miao Letter Reformed Tone-8</title><code>&amp;#94111;</code></item159></characters></category>
