<?xml version="1.0"?>
<category><title>Miscellaneous Symbols</title><characters><item0><title>Black Sun With Rays</title><code>&amp;#9728;</code></item0><item1><title>Cloud</title><code>&amp;#9729;</code></item1><item2><title>Umbrella</title><code>&amp;#9730;</code></item2><item3><title>Snowman</title><code>&amp;#9731;</code></item3><item4><title>Comet</title><code>&amp;#9732;</code></item4><item5><title>Black Star</title><code>&amp;#9733;</code></item5><item6><title>White Star</title><code>&amp;#9734;</code></item6><item7><title>Lightning</title><code>&amp;#9735;</code></item7><item8><title>Thunderstorm</title><code>&amp;#9736;</code></item8><item9><title>Sun</title><code>&amp;#9737;</code></item9><item10><title>Ascending Node</title><code>&amp;#9738;</code></item10><item11><title>Descending Node</title><code>&amp;#9739;</code></item11><item12><title>Conjunction</title><code>&amp;#9740;</code></item12><item13><title>Opposition</title><code>&amp;#9741;</code></item13><item14><title>Black Telephone</title><code>&amp;#9742;</code></item14><item15><title>White Telephone</title><code>&amp;#9743;</code></item15><item16><title>Ballot Box</title><code>&amp;#9744;</code></item16><item17><title>Ballot Box With Check</title><code>&amp;#9745;</code></item17><item18><title>Ballot Box With X</title><code>&amp;#9746;</code></item18><item19><title>Saltire</title><code>&amp;#9747;</code></item19><item20><title>Umbrella With Rain Drops</title><code>&amp;#9748;</code></item20><item21><title>Hot Beverage</title><code>&amp;#9749;</code></item21><item22><title>White Shogi Piece</title><code>&amp;#9750;</code></item22><item23><title>Black Shogi Piece</title><code>&amp;#9751;</code></item23><item24><title>Shamrock</title><code>&amp;#9752;</code></item24><item25><title>Reversed Rotated Floral Heart Bullet</title><code>&amp;#9753;</code></item25><item26><title>Black Left Pointing Index</title><code>&amp;#9754;</code></item26><item27><title>Black Right Pointing Index</title><code>&amp;#9755;</code></item27><item28><title>White Left Pointing Index</title><code>&amp;#9756;</code></item28><item29><title>White Up Pointing Index</title><code>&amp;#9757;</code></item29><item30><title>White Right Pointing Index</title><code>&amp;#9758;</code></item30><item31><title>White Down Pointing Index</title><code>&amp;#9759;</code></item31><item32><title>Skull And Crossbones</title><code>&amp;#9760;</code></item32><item33><title>Caution Sign</title><code>&amp;#9761;</code></item33><item34><title>Radioactive Sign</title><code>&amp;#9762;</code></item34><item35><title>Biohazard Sign</title><code>&amp;#9763;</code></item35><item36><title>Caduceus</title><code>&amp;#9764;</code></item36><item37><title>Ankh</title><code>&amp;#9765;</code></item37><item38><title>Orthodox Cross</title><code>&amp;#9766;</code></item38><item39><title>Chi Rho</title><code>&amp;#9767;</code></item39><item40><title>Cross Of Lorraine</title><code>&amp;#9768;</code></item40><item41><title>Cross Of Jerusalem</title><code>&amp;#9769;</code></item41><item42><title>Star And Crescent</title><code>&amp;#9770;</code></item42><item43><title>Farsi Symbol</title><code>&amp;#9771;</code></item43><item44><title>Adi Shakti</title><code>&amp;#9772;</code></item44><item45><title>Hammer And Sickle</title><code>&amp;#9773;</code></item45><item46><title>Peace Symbol</title><code>&amp;#9774;</code></item46><item47><title>Yin Yang</title><code>&amp;#9775;</code></item47><item48><title>Trigram For Heaven</title><code>&amp;#9776;</code></item48><item49><title>Trigram For Lake</title><code>&amp;#9777;</code></item49><item50><title>Trigram For Fire</title><code>&amp;#9778;</code></item50><item51><title>Trigram For Thunder</title><code>&amp;#9779;</code></item51><item52><title>Trigram For Wind</title><code>&amp;#9780;</code></item52><item53><title>Trigram For Water</title><code>&amp;#9781;</code></item53><item54><title>Trigram For Mountain</title><code>&amp;#9782;</code></item54><item55><title>Trigram For Earth</title><code>&amp;#9783;</code></item55><item56><title>Wheel Of Dharma</title><code>&amp;#9784;</code></item56><item57><title>White Frowning Face</title><code>&amp;#9785;</code></item57><item58><title>White Smiling Face</title><code>&amp;#9786;</code></item58><item59><title>Black Smiling Face</title><code>&amp;#9787;</code></item59><item60><title>White Sun With Rays</title><code>&amp;#9788;</code></item60><item61><title>First Quarter Moon</title><code>&amp;#9789;</code></item61><item62><title>Last Quarter Moon</title><code>&amp;#9790;</code></item62><item63><title>Mercury</title><code>&amp;#9791;</code></item63><item64><title>Female Sign</title><code>&amp;#9792;</code></item64><item65><title>Earth</title><code>&amp;#9793;</code></item65><item66><title>Male Sign</title><code>&amp;#9794;</code></item66><item67><title>Jupiter</title><code>&amp;#9795;</code></item67><item68><title>Saturn</title><code>&amp;#9796;</code></item68><item69><title>Uranus</title><code>&amp;#9797;</code></item69><item70><title>Neptune</title><code>&amp;#9798;</code></item70><item71><title>Pluto</title><code>&amp;#9799;</code></item71><item72><title>Aries</title><code>&amp;#9800;</code></item72><item73><title>Taurus</title><code>&amp;#9801;</code></item73><item74><title>Gemini</title><code>&amp;#9802;</code></item74><item75><title>Cancer</title><code>&amp;#9803;</code></item75><item76><title>Leo</title><code>&amp;#9804;</code></item76><item77><title>Virgo</title><code>&amp;#9805;</code></item77><item78><title>Libra</title><code>&amp;#9806;</code></item78><item79><title>Scorpius</title><code>&amp;#9807;</code></item79><item80><title>Sagittarius</title><code>&amp;#9808;</code></item80><item81><title>Capricorn</title><code>&amp;#9809;</code></item81><item82><title>Aquarius</title><code>&amp;#9810;</code></item82><item83><title>Pisces</title><code>&amp;#9811;</code></item83><item84><title>White Chess King</title><code>&amp;#9812;</code></item84><item85><title>White Chess Queen</title><code>&amp;#9813;</code></item85><item86><title>White Chess Rook</title><code>&amp;#9814;</code></item86><item87><title>White Chess Bishop</title><code>&amp;#9815;</code></item87><item88><title>White Chess Knight</title><code>&amp;#9816;</code></item88><item89><title>White Chess Pawn</title><code>&amp;#9817;</code></item89><item90><title>Black Chess King</title><code>&amp;#9818;</code></item90><item91><title>Black Chess Queen</title><code>&amp;#9819;</code></item91><item92><title>Black Chess Rook</title><code>&amp;#9820;</code></item92><item93><title>Black Chess Bishop</title><code>&amp;#9821;</code></item93><item94><title>Black Chess Knight</title><code>&amp;#9822;</code></item94><item95><title>Black Chess Pawn</title><code>&amp;#9823;</code></item95><item96><title>Black Spade Suit</title><code>&amp;#9824;</code></item96><item97><title>White Heart Suit</title><code>&amp;#9825;</code></item97><item98><title>White Diamond Suit</title><code>&amp;#9826;</code></item98><item99><title>Black Club Suit</title><code>&amp;#9827;</code></item99><item100><title>White Spade Suit</title><code>&amp;#9828;</code></item100><item101><title>Black Heart Suit</title><code>&amp;#9829;</code></item101><item102><title>Black Diamond Suit</title><code>&amp;#9830;</code></item102><item103><title>White Club Suit</title><code>&amp;#9831;</code></item103><item104><title>Hot Springs</title><code>&amp;#9832;</code></item104><item105><title>Quarter Note</title><code>&amp;#9833;</code></item105><item106><title>Eighth Note</title><code>&amp;#9834;</code></item106><item107><title>Beamed Eighth Notes</title><code>&amp;#9835;</code></item107><item108><title>Beamed Sixteenth Notes</title><code>&amp;#9836;</code></item108><item109><title>Music Flat Sign</title><code>&amp;#9837;</code></item109><item110><title>Music Natural Sign</title><code>&amp;#9838;</code></item110><item111><title>Music Sharp Sign</title><code>&amp;#9839;</code></item111><item112><title>West Syriac Cross</title><code>&amp;#9840;</code></item112><item113><title>East Syriac Cross</title><code>&amp;#9841;</code></item113><item114><title>Universal Recycling Symbol</title><code>&amp;#9842;</code></item114><item115><title>Recycling Symbol For Type-1 Plastics</title><code>&amp;#9843;</code></item115><item116><title>Recycling Symbol For Type-2 Plastics</title><code>&amp;#9844;</code></item116><item117><title>Recycling Symbol For Type-3 Plastics</title><code>&amp;#9845;</code></item117><item118><title>Recycling Symbol For Type-4 Plastics</title><code>&amp;#9846;</code></item118><item119><title>Recycling Symbol For Type-5 Plastics</title><code>&amp;#9847;</code></item119><item120><title>Recycling Symbol For Type-6 Plastics</title><code>&amp;#9848;</code></item120><item121><title>Recycling Symbol For Type-7 Plastics</title><code>&amp;#9849;</code></item121><item122><title>Recycling Symbol For Generic Materials</title><code>&amp;#9850;</code></item122><item123><title>Black Universal Recycling Symbol</title><code>&amp;#9851;</code></item123><item124><title>Recycled Paper Symbol</title><code>&amp;#9852;</code></item124><item125><title>Partially-Recycled Paper Symbol</title><code>&amp;#9853;</code></item125><item126><title>Permanent Paper Sign</title><code>&amp;#9854;</code></item126><item127><title>Wheelchair Symbol</title><code>&amp;#9855;</code></item127><item128><title>Die Face-1</title><code>&amp;#9856;</code></item128><item129><title>Die Face-2</title><code>&amp;#9857;</code></item129><item130><title>Die Face-3</title><code>&amp;#9858;</code></item130><item131><title>Die Face-4</title><code>&amp;#9859;</code></item131><item132><title>Die Face-5</title><code>&amp;#9860;</code></item132><item133><title>Die Face-6</title><code>&amp;#9861;</code></item133><item134><title>White Circle With Dot Right</title><code>&amp;#9862;</code></item134><item135><title>White Circle With Two Dots</title><code>&amp;#9863;</code></item135><item136><title>Black Circle With White Dot Right</title><code>&amp;#9864;</code></item136><item137><title>Black Circle With Two White Dots</title><code>&amp;#9865;</code></item137><item138><title>Monogram For Yang</title><code>&amp;#9866;</code></item138><item139><title>Monogram For Yin</title><code>&amp;#9867;</code></item139><item140><title>Digram For Greater Yang</title><code>&amp;#9868;</code></item140><item141><title>Digram For Lesser Yin</title><code>&amp;#9869;</code></item141><item142><title>Digram For Lesser Yang</title><code>&amp;#9870;</code></item142><item143><title>Digram For Greater Yin</title><code>&amp;#9871;</code></item143><item144><title>White Flag</title><code>&amp;#9872;</code></item144><item145><title>Black Flag</title><code>&amp;#9873;</code></item145><item146><title>Hammer And Pick</title><code>&amp;#9874;</code></item146><item147><title>Anchor</title><code>&amp;#9875;</code></item147><item148><title>Crossed Swords</title><code>&amp;#9876;</code></item148><item149><title>Staff Of Aesculapius</title><code>&amp;#9877;</code></item149><item150><title>Scales</title><code>&amp;#9878;</code></item150><item151><title>Alembic</title><code>&amp;#9879;</code></item151><item152><title>Flower</title><code>&amp;#9880;</code></item152><item153><title>Gear</title><code>&amp;#9881;</code></item153><item154><title>Staff Of Hermes</title><code>&amp;#9882;</code></item154><item155><title>Atom Symbol</title><code>&amp;#9883;</code></item155><item156><title>Fleur-De-Lis</title><code>&amp;#9884;</code></item156><item157><title>Outlined White Star</title><code>&amp;#9885;</code></item157><item158><title>Three Lines Converging Right</title><code>&amp;#9886;</code></item158><item159><title>Three Lines Converging Left</title><code>&amp;#9887;</code></item159><item160><title>Warning Sign</title><code>&amp;#9888;</code></item160><item161><title>High Voltage Sign</title><code>&amp;#9889;</code></item161><item162><title>Doubled Female Sign</title><code>&amp;#9890;</code></item162><item163><title>Doubled Male Sign</title><code>&amp;#9891;</code></item163><item164><title>Interlocked Female And Male Sign</title><code>&amp;#9892;</code></item164><item165><title>Male And Female Sign</title><code>&amp;#9893;</code></item165><item166><title>Male With Stroke Sign</title><code>&amp;#9894;</code></item166><item167><title>Male With Stroke And Male And Female Sign</title><code>&amp;#9895;</code></item167><item168><title>Vertical Male With Stroke Sign</title><code>&amp;#9896;</code></item168><item169><title>Horizontal Male With Stroke Sign</title><code>&amp;#9897;</code></item169><item170><title>Medium White Circle</title><code>&amp;#9898;</code></item170><item171><title>Medium Black Circle</title><code>&amp;#9899;</code></item171><item172><title>Medium Small White Circle</title><code>&amp;#9900;</code></item172><item173><title>Marriage Symbol</title><code>&amp;#9901;</code></item173><item174><title>Divorce Symbol</title><code>&amp;#9902;</code></item174><item175><title>Unmarried Partnership Symbol</title><code>&amp;#9903;</code></item175><item176><title>Coffin</title><code>&amp;#9904;</code></item176><item177><title>Funeral Urn</title><code>&amp;#9905;</code></item177><item178><title>Neuter</title><code>&amp;#9906;</code></item178><item179><title>Ceres</title><code>&amp;#9907;</code></item179><item180><title>Pallas</title><code>&amp;#9908;</code></item180><item181><title>Juno</title><code>&amp;#9909;</code></item181><item182><title>Vesta</title><code>&amp;#9910;</code></item182><item183><title>Chiron</title><code>&amp;#9911;</code></item183><item184><title>Black Moon Lilith</title><code>&amp;#9912;</code></item184><item185><title>Sextile</title><code>&amp;#9913;</code></item185><item186><title>Semisextile</title><code>&amp;#9914;</code></item186><item187><title>Quincunx</title><code>&amp;#9915;</code></item187><item188><title>Sesquiquadrate</title><code>&amp;#9916;</code></item188><item189><title>Soccer Ball</title><code>&amp;#9917;</code></item189><item190><title>Baseball</title><code>&amp;#9918;</code></item190><item191><title>Squared Key</title><code>&amp;#9919;</code></item191><item192><title>White Draughts Man</title><code>&amp;#9920;</code></item192><item193><title>White Draughts King</title><code>&amp;#9921;</code></item193><item194><title>Black Draughts Man</title><code>&amp;#9922;</code></item194><item195><title>Black Draughts King</title><code>&amp;#9923;</code></item195><item196><title>Snowman Without Snow</title><code>&amp;#9924;</code></item196><item197><title>Sun Behind Cloud</title><code>&amp;#9925;</code></item197><item198><title>Rain</title><code>&amp;#9926;</code></item198><item199><title>Black Snowman</title><code>&amp;#9927;</code></item199><item200><title>Thunder Cloud And Rain</title><code>&amp;#9928;</code></item200><item201><title>Turned White Shogi Piece</title><code>&amp;#9929;</code></item201><item202><title>Turned Black Shogi Piece</title><code>&amp;#9930;</code></item202><item203><title>White Diamond In Square</title><code>&amp;#9931;</code></item203><item204><title>Crossing Lanes</title><code>&amp;#9932;</code></item204><item205><title>Disabled Car</title><code>&amp;#9933;</code></item205><item206><title>Ophiuchus</title><code>&amp;#9934;</code></item206><item207><title>Pick</title><code>&amp;#9935;</code></item207><item208><title>Car Sliding</title><code>&amp;#9936;</code></item208><item209><title>Helmet With White Cross</title><code>&amp;#9937;</code></item209><item210><title>Circled Crossing Lanes</title><code>&amp;#9938;</code></item210><item211><title>Chains</title><code>&amp;#9939;</code></item211><item212><title>No Entry</title><code>&amp;#9940;</code></item212><item213><title>Alternate One-Way Left Way Traffic</title><code>&amp;#9941;</code></item213><item214><title>Black Two-Way Left Way Traffic</title><code>&amp;#9942;</code></item214><item215><title>White Two-Way Left Way Traffic</title><code>&amp;#9943;</code></item215><item216><title>Black Left Lane Merge</title><code>&amp;#9944;</code></item216><item217><title>White Left Lane Merge</title><code>&amp;#9945;</code></item217><item218><title>Drive Slow Sign</title><code>&amp;#9946;</code></item218><item219><title>Heavy White Down-Pointing Triangle</title><code>&amp;#9947;</code></item219><item220><title>Left Closed Entry</title><code>&amp;#9948;</code></item220><item221><title>Squared Saltire</title><code>&amp;#9949;</code></item221><item222><title>Falling Diagonal In White Circle In Black Square</title><code>&amp;#9950;</code></item222><item223><title>Black Truck</title><code>&amp;#9951;</code></item223><item224><title>Restricted Left Entry-1</title><code>&amp;#9952;</code></item224><item225><title>Restricted Left Entry-2</title><code>&amp;#9953;</code></item225><item226><title>Astronomical Symbol For Uranus</title><code>&amp;#9954;</code></item226><item227><title>Heavy Circle With Stroke And Two Dots Above</title><code>&amp;#9955;</code></item227><item228><title>Pentagram</title><code>&amp;#9956;</code></item228><item229><title>Right-Handed Interlaced Pentagram</title><code>&amp;#9957;</code></item229><item230><title>Left-Handed Interlaced Pentagram</title><code>&amp;#9958;</code></item230><item231><title>Inverted Pentagram</title><code>&amp;#9959;</code></item231><item232><title>Black Cross On Shield</title><code>&amp;#9960;</code></item232><item233><title>Shinto Shrine</title><code>&amp;#9961;</code></item233><item234><title>Church</title><code>&amp;#9962;</code></item234><item235><title>Castle</title><code>&amp;#9963;</code></item235><item236><title>Historic Site</title><code>&amp;#9964;</code></item236><item237><title>Gear Without Hub</title><code>&amp;#9965;</code></item237><item238><title>Gear With Handles</title><code>&amp;#9966;</code></item238><item239><title>Map Symbol For Lighthouse</title><code>&amp;#9967;</code></item239><item240><title>Mountain</title><code>&amp;#9968;</code></item240><item241><title>Umbrella On Ground</title><code>&amp;#9969;</code></item241><item242><title>Fountain</title><code>&amp;#9970;</code></item242><item243><title>Flag In Hole</title><code>&amp;#9971;</code></item243><item244><title>Ferry</title><code>&amp;#9972;</code></item244><item245><title>Sailboat</title><code>&amp;#9973;</code></item245><item246><title>Square Four Corners</title><code>&amp;#9974;</code></item246><item247><title>Skier</title><code>&amp;#9975;</code></item247><item248><title>Ice Skate</title><code>&amp;#9976;</code></item248><item249><title>Person With Ball</title><code>&amp;#9977;</code></item249><item250><title>Tent</title><code>&amp;#9978;</code></item250><item251><title>Japanese Bank Symbol</title><code>&amp;#9979;</code></item251><item252><title>Headstone Graveyard Symbol</title><code>&amp;#9980;</code></item252><item253><title>Fuel Pump</title><code>&amp;#9981;</code></item253><item254><title>Cup On Black Square</title><code>&amp;#9982;</code></item254><item255><title>White Flag With Horizontal Middle Black Stripe</title><code>&amp;#9983;</code></item255></characters></category>
