<?xml version="1.0"?>
<category><title>Zanabazar Square</title><characters><item0><title>Zanabazar Square Letter A</title><code>&amp;#72192;</code></item0><item1><title>Zanabazar Square Vowel Sign I</title><code>&amp;#72193;</code></item1><item2><title>Zanabazar Square Vowel Sign Ue</title><code>&amp;#72194;</code></item2><item3><title>Zanabazar Square Vowel Sign U</title><code>&amp;#72195;</code></item3><item4><title>Zanabazar Square Vowel Sign E</title><code>&amp;#72196;</code></item4><item5><title>Zanabazar Square Vowel Sign Oe</title><code>&amp;#72197;</code></item5><item6><title>Zanabazar Square Vowel Sign O</title><code>&amp;#72198;</code></item6><item7><title>Zanabazar Square Vowel Sign Ai</title><code>&amp;#72199;</code></item7><item8><title>Zanabazar Square Vowel Sign Au</title><code>&amp;#72200;</code></item8><item9><title>Zanabazar Square Vowel Sign Reversed I</title><code>&amp;#72201;</code></item9><item10><title>Zanabazar Square Vowel Length Mark</title><code>&amp;#72202;</code></item10><item11><title>Zanabazar Square Letter Ka</title><code>&amp;#72203;</code></item11><item12><title>Zanabazar Square Letter Kha</title><code>&amp;#72204;</code></item12><item13><title>Zanabazar Square Letter Ga</title><code>&amp;#72205;</code></item13><item14><title>Zanabazar Square Letter Gha</title><code>&amp;#72206;</code></item14><item15><title>Zanabazar Square Letter Nga</title><code>&amp;#72207;</code></item15><item16><title>Zanabazar Square Letter Ca</title><code>&amp;#72208;</code></item16><item17><title>Zanabazar Square Letter Cha</title><code>&amp;#72209;</code></item17><item18><title>Zanabazar Square Letter Ja</title><code>&amp;#72210;</code></item18><item19><title>Zanabazar Square Letter Nya</title><code>&amp;#72211;</code></item19><item20><title>Zanabazar Square Letter Tta</title><code>&amp;#72212;</code></item20><item21><title>Zanabazar Square Letter Ttha</title><code>&amp;#72213;</code></item21><item22><title>Zanabazar Square Letter Dda</title><code>&amp;#72214;</code></item22><item23><title>Zanabazar Square Letter Ddha</title><code>&amp;#72215;</code></item23><item24><title>Zanabazar Square Letter Nna</title><code>&amp;#72216;</code></item24><item25><title>Zanabazar Square Letter Ta</title><code>&amp;#72217;</code></item25><item26><title>Zanabazar Square Letter Tha</title><code>&amp;#72218;</code></item26><item27><title>Zanabazar Square Letter Da</title><code>&amp;#72219;</code></item27><item28><title>Zanabazar Square Letter Dha</title><code>&amp;#72220;</code></item28><item29><title>Zanabazar Square Letter Na</title><code>&amp;#72221;</code></item29><item30><title>Zanabazar Square Letter Pa</title><code>&amp;#72222;</code></item30><item31><title>Zanabazar Square Letter Pha</title><code>&amp;#72223;</code></item31><item32><title>Zanabazar Square Letter Ba</title><code>&amp;#72224;</code></item32><item33><title>Zanabazar Square Letter Bha</title><code>&amp;#72225;</code></item33><item34><title>Zanabazar Square Letter Ma</title><code>&amp;#72226;</code></item34><item35><title>Zanabazar Square Letter Tsa</title><code>&amp;#72227;</code></item35><item36><title>Zanabazar Square Letter Tsha</title><code>&amp;#72228;</code></item36><item37><title>Zanabazar Square Letter Dza</title><code>&amp;#72229;</code></item37><item38><title>Zanabazar Square Letter Dzha</title><code>&amp;#72230;</code></item38><item39><title>Zanabazar Square Letter Zha</title><code>&amp;#72231;</code></item39><item40><title>Zanabazar Square Letter Za</title><code>&amp;#72232;</code></item40><item41><title>Zanabazar Square Letter -A</title><code>&amp;#72233;</code></item41><item42><title>Zanabazar Square Letter Ya</title><code>&amp;#72234;</code></item42><item43><title>Zanabazar Square Letter Ra</title><code>&amp;#72235;</code></item43><item44><title>Zanabazar Square Letter La</title><code>&amp;#72236;</code></item44><item45><title>Zanabazar Square Letter Va</title><code>&amp;#72237;</code></item45><item46><title>Zanabazar Square Letter Sha</title><code>&amp;#72238;</code></item46><item47><title>Zanabazar Square Letter Ssa</title><code>&amp;#72239;</code></item47><item48><title>Zanabazar Square Letter Sa</title><code>&amp;#72240;</code></item48><item49><title>Zanabazar Square Letter Ha</title><code>&amp;#72241;</code></item49><item50><title>Zanabazar Square Letter Kssa</title><code>&amp;#72242;</code></item50><item51><title>Zanabazar Square Final Consonant Mark</title><code>&amp;#72243;</code></item51><item52><title>Zanabazar Square Sign Virama</title><code>&amp;#72244;</code></item52><item53><title>Zanabazar Square Sign Candrabindu</title><code>&amp;#72245;</code></item53><item54><title>Zanabazar Square Sign Candrabindu With Ornament</title><code>&amp;#72246;</code></item54><item55><title>Zanabazar Square Sign Candra With Ornament</title><code>&amp;#72247;</code></item55><item56><title>Zanabazar Square Sign Anusvara</title><code>&amp;#72248;</code></item56><item57><title>Zanabazar Square Sign Visarga</title><code>&amp;#72249;</code></item57><item58><title>Zanabazar Square Cluster-Initial Letter Ra</title><code>&amp;#72250;</code></item58><item59><title>Zanabazar Square Cluster-Final Letter Ya</title><code>&amp;#72251;</code></item59><item60><title>Zanabazar Square Cluster-Final Letter Ra</title><code>&amp;#72252;</code></item60><item61><title>Zanabazar Square Cluster-Final Letter La</title><code>&amp;#72253;</code></item61><item62><title>Zanabazar Square Cluster-Final Letter Va</title><code>&amp;#72254;</code></item62><item63><title>Zanabazar Square Initial Head Mark</title><code>&amp;#72255;</code></item63><item64><title>Zanabazar Square Closing Head Mark</title><code>&amp;#72256;</code></item64><item65><title>Zanabazar Square Mark Tsheg</title><code>&amp;#72257;</code></item65><item66><title>Zanabazar Square Mark Shad</title><code>&amp;#72258;</code></item66><item67><title>Zanabazar Square Mark Double Shad</title><code>&amp;#72259;</code></item67><item68><title>Zanabazar Square Mark Long Tsheg</title><code>&amp;#72260;</code></item68><item69><title>Zanabazar Square Initial Double-Lined Head Mark</title><code>&amp;#72261;</code></item69><item70><title>Zanabazar Square Closing Double-Lined Head Mark</title><code>&amp;#72262;</code></item70><item71><title>Zanabazar Square Subjoiner</title><code>&amp;#72263;</code></item71><item72><title>Utf-8 Character</title><code>&amp;#72264;</code></item72><item73><title>Utf-8 Character</title><code>&amp;#72265;</code></item73><item74><title>Utf-8 Character</title><code>&amp;#72266;</code></item74><item75><title>Utf-8 Character</title><code>&amp;#72267;</code></item75><item76><title>Utf-8 Character</title><code>&amp;#72268;</code></item76><item77><title>Utf-8 Character</title><code>&amp;#72269;</code></item77><item78><title>Utf-8 Character</title><code>&amp;#72270;</code></item78><item79><title>Utf-8 Character</title><code>&amp;#72271;</code></item79></characters></category>
